vartastorage/__init__.py
vartastorage/cgi_client.py
vartastorage/cgi_data.py
vartastorage/modbus_client.py
vartastorage/vartastorage.py
vartastorage-0.4.2.dist-info/METADATA
vartastorage-0.4.2.dist-info/WHEEL
vartastorage-0.4.2.dist-info/top_level.txt
vartastorage-0.4.2.dist-info/RECORD
