Metadata-Version: 2.4
Name: vartastorage
Version: 0.4.2
Summary: VARTA Battery
Home-page: http://github.com/vip0r/vartastorage
Author: edAndy
Author-email: an-dy@gmx.de
License: APACHE
Requires-Python: >=3.11
Requires-Dist: pymodbus>=3.11.0
Requires-Dist: requests
Dynamic: author
Dynamic: author-email
Dynamic: description
Dynamic: home-page
Dynamic: license
Dynamic: requires-dist
Dynamic: requires-python
Dynamic: summary
